netskope/__init__.py
netskope/netskope.py
netskope/privateapps.py
netskope-0.1.2.dist-info/LICENSE
netskope-0.1.2.dist-info/METADATA
netskope-0.1.2.dist-info/WHEEL
netskope-0.1.2.dist-info/top_level.txt
netskope-0.1.2.dist-info/RECORD
