Metadata-Version: 2.1
Name: netskope
Version: 0.1.2
Summary: Netskope API Wrapper Module
Home-page: https://github.com/neerdael-nl/python-netskope
Author: John Neerdael
Author-email: jneerdael@netskope.com
License: BSD-2-Clause
Project-URL: Documentation, https://python-netskope.readthedocs.io/en/latest/
Project-URL: Source, https://github.com/neerdael-nl/python-netskope
Project-URL: Tracker, https://github.com/neerdael-nl/python-netskope/issues
Classifier: Programming Language :: Python :: 3
Classifier: License :: OSI Approved :: BSD License
Classifier: Operating System :: OS Independent
Requires-Python: >=3.7
License-File: LICENSE
Requires-Dist: requests
Requires-Dist: pyyaml
